dynamic_smtp/__init__.py
dynamic_smtp/admin.py
dynamic_smtp/apps.py
dynamic_smtp/email.py
dynamic_smtp/models.py
dynamic_smtp/locale/pt_BR/LC_MESSAGES/django.po
dynamic_smtp/migrations/0001_initial.py
dynamic_smtp/migrations/__init__.py
django_dynamic_smtp-0.0.8.dist-info/METADATA
django_dynamic_smtp-0.0.8.dist-info/WHEEL
django_dynamic_smtp-0.0.8.dist-info/licenses/LICENSE
django_dynamic_smtp-0.0.8.dist-info/RECORD
