Metadata-Version: 2.4
Name: django-dynamic-smtp
Version: 0.0.8
Summary: Configure email settings in the admin
Project-URL: Homepage, https://gitlab.com/joaoseckler/django-dynamic-smtp
Project-URL: Issues, https://gitlab.com/joaoseckler/django-dynamic-smtp/issues
Author-email: João Seckler <jseckler@riseup.net>
License-Expression: MIT
License-File: LICENSE
Classifier: Operating System :: OS Independent
Classifier: Programming Language :: Python :: 3
Requires-Python: >=3.7
Requires-Dist: beautifulsoup4
Requires-Dist: django
Requires-Dist: django-object-actions
Requires-Dist: django-solo
Requires-Dist: django-tinymce
Requires-Dist: lxml
